es7s_commons/__init__.py
es7s_commons/_version.py
es7s_commons/column.py
es7s_commons/common.py
es7s_commons/gradient.py
es7s_commons/plang.py
es7s_commons/prof.py
es7s_commons/progressbar.py
es7s_commons/pt_.py
es7s_commons/scale.py
es7s_commons/separator.py
es7s_commons/spinner.py
es7s_commons/structx.py
es7s_commons/strutil.py
es7s_commons/termstate.py
es7s_commons/totalsize.py
es7s_commons/weather.py
es7s_commons-1.8.0.dist-info/METADATA
es7s_commons-1.8.0.dist-info/WHEEL
es7s_commons-1.8.0.dist-info/RECORD
