Metadata-Version: 2.1
Name: es7s.commons
Version: 1.8.0
Summary: es7s system common classes
Project-URL: Homepage, https://github.com/es7s/commons
Project-URL: Bug Tracker, https://github.com/es7s/commons/issues
Author-email: Aleksandr Shavykin <0.delameter@gmail.com>
License-Expression: LGPL-3.0
Keywords: ansi,color,console,format,terminal
Classifier: Development Status :: 5 - Production/Stable
Classifier: Intended Audience :: Developers
Classifier: Intended Audience :: System Administrators
Classifier: License :: OSI Approved :: GNU Lesser General Public License v3 (LGPLv3)
Classifier: Operating System :: OS Independent
Classifier: Programming Language :: Python
Classifier: Programming Language :: Python :: 3
Classifier: Programming Language :: Python :: 3.10
Classifier: Topic :: Software Development :: Libraries
Classifier: Topic :: Text Processing :: Filters
Classifier: Topic :: Text Processing :: General
Requires-Python: >=3.10
Requires-Dist: pytermor>=2.118.0.dev0
